{
    "name": "Kef-Sales-Connector",
    "config": {
      "connector.class": "io.debezium.connector.mysql.MySqlConnector",
      "tasksMax": 1,
      "database.hostname": "Kef_Host",
      "database.port": "3306",
      "database.user": "root",
      "database.password": "secret",
      "database.server.id": "3",
      "database.whitelist": "kef_sales_db",
      "table.whitelist": "kef_sales_db.kef_sales",
      "topic.prefix": "KefSales",
      "schema.history.internal.kafka.bootstrap.servers": "kafka:9092",
      "schema.history.internal.kafka.topic": "schemahistory.kef_sales_database"
    }
}  